Metadata-Version: 2.4
Name: x_make_github_visitor_x
Version: 12.0.1
Summary: Makes GitHub repository inspections.
Author-email: RRGM of the Primus Pilus Night Watch AI Corporation <eye4357@outlook.com>
License-Expression: MIT
